fluxcomp-0.1.6.dist-info/METADATA
fluxcomp-0.1.6.dist-info/WHEEL
fluxcomp-0.1.6.dist-info/entry_points.txt
fluxcomp-0.1.6.dist-info/licenses/LICENSE
fluxcomp/__init__.py
fluxcomp/constants.py
fluxcomp/cosmic_ray_fluxes.py
fluxcomp/flux.py
fluxcomp/gsf_data_table.txt
fluxcomp/muon_fluxes.py
fluxcomp/version.py
fluxcomp-0.1.6.dist-info/RECORD
