Metadata-Version: 2.1
Name: FluxComp
Version: 0.1.6
Summary: (ensator) provides numpy and pandas compatible implemenntations of cosmic ray flux models as well as calculation for simulation weights.
Author-Email: Ludwig Neste <ludwig.neste@fysik.su.se>
License: MIT
Project-URL: homepage, https://github.com/The-Ludwig/FluxComp
Project-URL: repository, https://github.com/The-Ludwig/FluxComp
Project-URL: documentation, https://fluxcomp.readthedocs.io/en/latest/
Requires-Python: >=3.8
Requires-Dist: numpy
Requires-Dist: pandas
Requires-Dist: particle
Requires-Dist: scipy
